flask_swagger_plus
